feishu_tools/feishu_tools.py
feishu_tools/setting.py
feishu_tools-1.0.1.dist-info/METADATA
feishu_tools-1.0.1.dist-info/WHEEL
feishu_tools-1.0.1.dist-info/top_level.txt
feishu_tools-1.0.1.dist-info/RECORD
