Metadata-Version: 2.4
Name: feishu_tools
Version: 1.0.1
Summary: 一个飞书工具集
Requires-Python: >=3.8
Requires-Dist: lark_oapi
Requires-Dist: python-dotenv
